README.md
setup.py
xline/__init__.py
xline/base_classes.py
xline/elements.py
xline/line.py
xline/loader_mad.py
xline/loader_sixtrack.py
xline/mathlibs.py
xline/particles.py
xline.egg-info/PKG-INFO
xline.egg-info/SOURCES.txt
xline.egg-info/dependency_links.txt
xline.egg-info/requires.txt
xline.egg-info/top_level.txt
xline/be_beamfields/BB6D.py
xline/be_beamfields/BB6Ddata.py
xline/be_beamfields/__init__.py
xline/be_beamfields/beambeam.py
xline/be_beamfields/boost.py
xline/be_beamfields/gaussian_fields.py
xline/be_beamfields/propagate_sigma_matrix.py
xline/be_beamfields/qgauss.py
xline/be_beamfields/slicing.py
xline/be_beamfields/spacecharge.py