Metadata-Version: 1.0
Name: xline
Version: 0.0.11
Summary: 6D Tracking Code
Home-page: https://github.com/rdemaria/xline
Author: Riccardo De Maria, Giovanni Iadarola
Author-email: riccardo.de.maria@cern.ch
License: UNKNOWN
Platform: UNKNOWN
